ai4_metadata/__init__.py
ai4_metadata/assets/examples/invalid.json
ai4_metadata/assets/examples/sample-v1.mods.json
ai4_metadata/assets/examples/sample-v1.mods.yaml
ai4_metadata/assets/examples/sample-v2.mods.json
ai4_metadata/assets/examples/sample-v2.mods.yaml
ai4_metadata/assets/examples/sample-v2.pytho.json
ai4_metadata/assets/json-ld/mldcat-ap-context-2.0.0.jsonld
ai4_metadata/assets/rdf/ai4eosc-category.ttl
ai4_metadata/assets/rdf/ai4eosc-library.ttl
ai4_metadata/assets/rdf/ai4eosc-tasktype.ttl
ai4_metadata/assets/schemata/ai4-apps-v1.0.0.json
ai4_metadata/assets/schemata/ai4-apps-v1.0.0.json.invalid
ai4_metadata/assets/schemata/ai4-apps-v2.0.0.json
ai4_metadata/assets/schemata/ai4-apps-v2.1.0.json
ai4_metadata/assets/schemata/ai4-apps-v2.2.0.json
ai4_metadata/assets/schemata/ai4-apps-v2.3.0.json
ai4_metadata/cli.py
ai4_metadata/exceptions.py
ai4_metadata/generate.py
ai4_metadata/mapping/__init__.py
ai4_metadata/mapping/profiles/__init__.py
ai4_metadata/mapping/profiles/mldcatap.py
ai4_metadata/metadata.py
ai4_metadata/migrate.py
ai4_metadata/sphinxext.py
ai4_metadata/tests/__init__.py
ai4_metadata/tests/conftest.py
ai4_metadata/tests/test_cli.py
ai4_metadata/tests/test_metadata.py
ai4_metadata/tests/test_migrate.py
ai4_metadata/tests/test_mldcat.py
ai4_metadata/tests/test_utils.py
ai4_metadata/tests/test_validator.py
ai4_metadata/utils.py
ai4_metadata/validate.py
ai4_metadata-2.4.2.dist-info/METADATA
ai4_metadata-2.4.2.dist-info/WHEEL
ai4_metadata-2.4.2.dist-info/entry_points.txt
ai4_metadata-2.4.2.dist-info/licenses/LICENSE
ai4_metadata-2.4.2.dist-info/RECORD
