Metadata-Version: 2.4
Name: ai4-metadata
Version: 2.4.2
Summary: AI4OS Hub applications metadata utilities
License: Apache-2
License-File: LICENSE
Author: Álvaro López García
Author-email: aloga@ifca.unican.es
Requires-Python: >=3.10,<4.0
Classifier: Development Status :: 5 - Production/Stable
Classifier: Environment :: Console
Classifier: Intended Audience :: Developers
Classifier: License :: OSI Approved :: Apache Software License
Classifier: License :: Other/Proprietary License
Classifier: Programming Language :: Python :: 3
Classifier: Programming Language :: Python :: 3.10
Classifier: Programming Language :: Python :: 3.11
Classifier: Programming Language :: Python :: 3.12
Classifier: Programming Language :: Python :: 3.13
Classifier: Programming Language :: Python :: 3.14
Classifier: Topic :: Scientific/Engineering :: Artificial Intelligence
Classifier: Topic :: Software Development :: Libraries :: Python Modules
Requires-Dist: jsonschema (>=4.25.0,<5.0.0)
Requires-Dist: pyyaml (>=6.0.2,<7.0.0)
Requires-Dist: rdflib (>=7.1.3,<8.0.0)
Requires-Dist: rfc3987 (>=1.3.8,<2.0.0)
Requires-Dist: typer (>=0.20.0,<0.21.0)
Project-URL: Bug Tracker, https://github.com/ai4os/ai4-metadata/issues
Project-URL: Homepage, https://github.com/ai4os/ai4-metadata
Project-URL: Repository, https://github.com/ai4os/ai4-metadata
